{"chunk_definitions":[{"row":7,"row_count":1,"visible":true,"expansion_state":0,"options":{"engine":"r","label":"options","include":false},"document_id":"E84FEC8F","chunk_id":"cn5yrgwxc7dcz","chunk_label":"options"},{"row":31,"row_count":1,"visible":true,"expansion_state":0,"options":{"engine":"r","message":false,"warning":false,"label":"unnamed-chunk-4"},"document_id":"E84FEC8F","chunk_id":"ckgwlbym0d2fn","chunk_label":"unnamed-chunk-1"},{"row":49,"row_count":1,"visible":true,"expansion_state":0,"options":{"engine":"r","label":"unnamed-chunk-2"},"document_id":"E84FEC8F","chunk_id":"cvf2myyy247k4","chunk_label":"unnamed-chunk-2"},{"row":57,"row_count":1,"visible":true,"expansion_state":0,"options":{"engine":"r","label":"unnamed-chunk-3"},"document_id":"E84FEC8F","chunk_id":"c1r8rdhgjcyrn","chunk_label":"unnamed-chunk-3"},{"row":90,"row_count":1,"visible":true,"expansion_state":0,"options":{"engine":"r","message":false,"label":"unnamed-chunk-4"},"document_id":"6820EFE5","chunk_id":"c3r4zk3kz6jhp","chunk_label":"unnamed-chunk-4"},{"row":110,"row_count":1,"visible":true,"expansion_state":0,"options":{"engine":"r","label":"unnamed-chunk-5"},"document_id":"6820EFE5","chunk_id":"csn12k0zpmva0","chunk_label":"unnamed-chunk-5"},{"row":166,"row_count":1,"visible":true,"expansion_state":0,"options":{"engine":"r","message":false,"label":"unnamed-chunk-6"},"document_id":"6820EFE5","chunk_id":"cqy0461rziq1l","chunk_label":"unnamed-chunk-6"},{"row":185,"row_count":1,"visible":true,"expansion_state":0,"options":{"engine":"r","label":"unnamed-chunk-7"},"document_id":"6820EFE5","chunk_id":"cayymw7mkjebs","chunk_label":"unnamed-chunk-7"},{"row":193,"row_count":1,"visible":true,"expansion_state":0,"options":{"engine":"r","label":"unnamed-chunk-8"},"document_id":"6820EFE5","chunk_id":"cukf5manodyy1","chunk_label":"unnamed-chunk-8"},{"row":223,"row_count":1,"visible":true,"expansion_state":0,"options":{"engine":"r","message":false,"label":"unnamed-chunk-9"},"document_id":"6820EFE5","chunk_id":"cw9u36x1bv99j","chunk_label":"unnamed-chunk-9"},{"row":243,"row_count":1,"visible":true,"expansion_state":0,"options":{"engine":"r","label":"unnamed-chunk-10"},"document_id":"6820EFE5","chunk_id":"cdrqk6var99tn","chunk_label":"unnamed-chunk-10"},{"row":261,"row_count":1,"visible":true,"expansion_state":0,"options":{"engine":"r","label":"unnamed-chunk-11"},"document_id":"6820EFE5","chunk_id":"cbzns9zraph4a","chunk_label":"unnamed-chunk-11"},{"row":286,"row_count":1,"visible":true,"expansion_state":0,"options":{"engine":"r","message":false,"label":"unnamed-chunk-13"},"document_id":"6820EFE5","chunk_id":"cdzc6fxyqcwuu","chunk_label":"unnamed-chunk-12"},{"row":312,"row_count":1,"visible":true,"expansion_state":0,"options":{"engine":"r","label":"unnamed-chunk-14"},"document_id":"6820EFE5","chunk_id":"cspfo0vl106mf","chunk_label":"unnamed-chunk-13"},{"row":324,"row_count":1,"visible":true,"expansion_state":0,"options":{"engine":"r","label":"unnamed-chunk-15"},"document_id":"6820EFE5","chunk_id":"cnru88vj129o0","chunk_label":"unnamed-chunk-14"},{"row":340,"row_count":1,"visible":true,"expansion_state":0,"options":{"engine":"r","label":"unnamed-chunk-16"},"document_id":"6820EFE5","chunk_id":"cycar393z7tf1","chunk_label":"unnamed-chunk-15"},{"row":358,"row_count":1,"visible":true,"expansion_state":0,"options":{"engine":"r","label":"unnamed-chunk-17"},"document_id":"6820EFE5","chunk_id":"cpxwjiek2hsic","chunk_label":"unnamed-chunk-16"},{"row":443,"row_count":1,"visible":true,"expansion_state":0,"options":{"engine":"r","label":"unnamed-chunk-1"},"document_id":"6820EFE5","chunk_id":"cphxedzp7ytmk","chunk_label":"unnamed-chunk-17"}],"doc_write_time":1611786414}