{"chunk_definitions":[{"row":7,"row_count":1,"visible":true,"expansion_state":0,"options":{"engine":"r","label":"options","include":false},"document_id":"DBFCCE6A","chunk_id":"cs5mrciqmbajr","chunk_label":"options"},{"row":25,"row_count":1,"visible":true,"expansion_state":0,"options":{"engine":"r","message":false,"label":"unnamed-chunk-1"},"document_id":"DBFCCE6A","chunk_id":"crojn2l6nii02","chunk_label":"unnamed-chunk-1"},{"row":41,"row_count":1,"visible":true,"expansion_state":0,"options":{"engine":"r","label":"unnamed-chunk-1"},"document_id":"DBFCCE6A","chunk_id":"ci433tytqjztl","chunk_label":"unnamed-chunk-2"},{"row":59,"row_count":1,"visible":true,"expansion_state":0,"options":{"engine":"r","label":"unnamed-chunk-1"},"document_id":"DBFCCE6A","chunk_id":"cfrg2xnow4psf","chunk_label":"unnamed-chunk-3"},{"row":77,"row_count":1,"visible":true,"expansion_state":0,"options":{"engine":"r","warning":false,"label":"unnamed-chunk-1"},"document_id":"DBFCCE6A","chunk_id":"con0udpsa4b55","chunk_label":"unnamed-chunk-4"},{"row":93,"row_count":1,"visible":true,"expansion_state":0,"options":{"engine":"r","label":"unnamed-chunk-1"},"document_id":"DBFCCE6A","chunk_id":"czownc0mkvke4","chunk_label":"unnamed-chunk-5"}],"doc_write_time":1606085262,"chunk_rendered_width":700}