{"chunk_definitions":[{"row":7,"row_count":1,"visible":true,"expansion_state":0,"options":{"engine":"r","label":"options","include":false},"document_id":"085F3319","chunk_id":"cwnpvtb26zlo2","chunk_label":"options"},{"row":29,"row_count":1,"visible":true,"expansion_state":0,"options":{"engine":"r","message":false,"warning":false,"label":"unnamed-chunk-1"},"document_id":"085F3319","chunk_id":"c5poagwqgdxw9","chunk_label":"unnamed-chunk-1"},{"row":57,"row_count":1,"visible":true,"expansion_state":0,"options":{"engine":"r","label":"unnamed-chunk-1"},"document_id":"085F3319","chunk_id":"ctw1f97cfpc33","chunk_label":"unnamed-chunk-3"}],"doc_write_time":1611352911}